exonize/__init__.py
exonize/classifier_handler.py
exonize/data_preprocessor.py
exonize/environment_setup.py
exonize/exonize.py
exonize/exonize_analysis.py
exonize/exonize_handler.py
exonize/profiling.py
exonize/reconciler_handler.py
exonize/searcher.py
exonize/sqlite_handler.py
exonize/.ipynb_checkpoints/reconciler_handler-checkpoint.py
exonize-1.1.2.dist-info/licenses/LICENSE
figures/phylo_figs/get-pip.py
tests/test_classification.py
tests/test_data_preprocessor.py
tests/test_reconciler_handler.py
tests/test_searcher.py
exonize-1.1.2.dist-info/METADATA
exonize-1.1.2.dist-info/WHEEL
exonize-1.1.2.dist-info/entry_points.txt
exonize-1.1.2.dist-info/top_level.txt
exonize-1.1.2.dist-info/RECORD
