Metadata-Version: 2.4
Name: exonize
Version: 1.1.2
Summary: A tool for finding duplicated exons in annotated genomes
Author: Marina Herrera Sarrias, Christopher Wheat, Liam Longo, Lars Arvestad
Maintainer-email: Lars Arvestad <arve@math.su.se>
License: MIT License
License-File: LICENSE
Requires-Dist: gffutils
Requires-Dist: portion
Requires-Dist: biopython
Requires-Dist: networkx
Requires-Dist: matplotlib
Requires-Dist: pandas
Dynamic: license-file
